anodict/__init__.py
anodict/anodict.py
anodict/test_dict_to_class.py
anodict-0.0.2.dist-info/LICENSE
anodict-0.0.2.dist-info/METADATA
anodict-0.0.2.dist-info/WHEEL
anodict-0.0.2.dist-info/top_level.txt
anodict-0.0.2.dist-info/RECORD
